jsontable/__init__.py
jsontable/jsontable.py
jsontable-0.1.1.dist-info/METADATA
jsontable-0.1.1.dist-info/WHEEL
jsontable-0.1.1.dist-info/license.txt
jsontable-0.1.1.dist-info/top_level.txt
jsontable-0.1.1.dist-info/RECORD
