Metadata-Version: 2.1
Name: jsontable
Version: 0.1.1
Summary: Convert a JSON to a table
Home-page: https://github.com/ernestomonroy/jsontable
Author: Ernesto Monroy
License: UNKNOWN
Project-URL: Bug Reports, https://github.com/ernestomonroy/jsontable/issues
Project-URL: Source, https://github.com/ernestomonroy/jsontable
Keywords: json mining etl extract transform etltools data parsing parse mapper relational table
Platform: UNKNOWN
Classifier: Development Status :: 3 - Alpha
Classifier: Intended Audience :: Developers
Classifier: Topic :: Utilities
Classifier: License :: OSI Approved :: MIT License
Classifier: Programming Language :: Python :: 3
Requires-Python: >=3.5
